odoo/addons/project_task_digitized_signature/README.rst
odoo/addons/project_task_digitized_signature/__init__.py
odoo/addons/project_task_digitized_signature/__manifest__.py
odoo/addons/project_task_digitized_signature/i18n/ar.po
odoo/addons/project_task_digitized_signature/i18n/ca.po
odoo/addons/project_task_digitized_signature/i18n/de.po
odoo/addons/project_task_digitized_signature/i18n/el.po
odoo/addons/project_task_digitized_signature/i18n/es.po
odoo/addons/project_task_digitized_signature/i18n/es_CR.po
odoo/addons/project_task_digitized_signature/i18n/es_MX.po
odoo/addons/project_task_digitized_signature/i18n/es_VE.po
odoo/addons/project_task_digitized_signature/i18n/fi.po
odoo/addons/project_task_digitized_signature/i18n/fr.po
odoo/addons/project_task_digitized_signature/i18n/gl.po
odoo/addons/project_task_digitized_signature/i18n/hr.po
odoo/addons/project_task_digitized_signature/i18n/hr_HR.po
odoo/addons/project_task_digitized_signature/i18n/hu.po
odoo/addons/project_task_digitized_signature/i18n/it.po
odoo/addons/project_task_digitized_signature/i18n/ja.po
odoo/addons/project_task_digitized_signature/i18n/lt.po
odoo/addons/project_task_digitized_signature/i18n/lv.po
odoo/addons/project_task_digitized_signature/i18n/mk.po
odoo/addons/project_task_digitized_signature/i18n/mn.po
odoo/addons/project_task_digitized_signature/i18n/nl.po
odoo/addons/project_task_digitized_signature/i18n/pl.po
odoo/addons/project_task_digitized_signature/i18n/project_task_digitized_signature.pot
odoo/addons/project_task_digitized_signature/i18n/pt.po
odoo/addons/project_task_digitized_signature/i18n/pt_BR.po
odoo/addons/project_task_digitized_signature/i18n/pt_PT.po
odoo/addons/project_task_digitized_signature/i18n/ro.po
odoo/addons/project_task_digitized_signature/i18n/sl.po
odoo/addons/project_task_digitized_signature/i18n/sv.po
odoo/addons/project_task_digitized_signature/i18n/tr.po
odoo/addons/project_task_digitized_signature/i18n/uk.po
odoo12_addon_project_task_digitized_signature-12.0.1.0.0.99.dev7.dist-info/METADATA
odoo12_addon_project_task_digitized_signature-12.0.1.0.0.99.dev7.dist-info/WHEEL
odoo12_addon_project_task_digitized_signature-12.0.1.0.0.99.dev7.dist-info/top_level.txt
odoo12_addon_project_task_digitized_signature-12.0.1.0.0.99.dev7.dist-info/RECORD
