Metadata-Version: 2.1
Name: odoo12-addon-project-task-digitized-signature
Version: 12.0.1.0.0.99.dev7
Summary: Project Task Digitized Signature
Home-page: https://github.com/OCA/project
Author: Tecnativa, Odoo Community Association (OCA)
Author-email: support@odoo-community.org
License: AGPL-3
Platform: UNKNOWN
Classifier: Programming Language :: Python
Classifier: Framework :: Odoo
Classifier: Framework :: Odoo :: 12.0
Classifier: License :: OSI Approved :: GNU Affero General Public License v3
Requires-Python: >=3.5
Requires-Dist: odoo12-addon-project-task-report
Requires-Dist: odoo12-addon-web-widget-digitized-signature
Requires-Dist: odoo <12.1dev,>=12.0a
